iarray_community/__init__.py
iarray_community/config_params.py
iarray_community/constructors.py
iarray_community/iarray.py
iarray_community/info.py
iarray_community/utils.py
iarray_community-0.0.4.dist-info/LICENSE
iarray_community-0.0.4.dist-info/METADATA
iarray_community-0.0.4.dist-info/WHEEL
iarray_community-0.0.4.dist-info/top_level.txt
iarray_community-0.0.4.dist-info/RECORD
