Metadata-Version: 2.1
Name: iarray-community
Version: 0.0.4
Summary: An efficient, flexible and fast toolkit for managing your data
Home-page: https://ironarray.io
Author: ironArray Development Team
Author-email: contact@ironarray.io
License: UNKNOWN
Project-URL: Bug Tracker, https://github.com/ironArray/iarray-community/issues
Platform: UNKNOWN
Classifier: Programming Language :: Python :: 3
Classifier: License :: OSI Approved :: GNU General Public License v3 (GPLv3)
Classifier: Operating System :: OS Independent
Requires-Python: >=3.7
License-File: LICENSE
Requires-Dist: caterva (>=0.6.0)
Requires-Dist: numpy
